hades/__init__.py
hades/data_loading/__init__.py
hades/data_loading/load_data.py
hades/data_loading/utils.py
hades/plots/__init__.py
hades/plots/simple_plots.py
hades/plots/topics.py
hades/summaries/__init__.py
hades/summaries/summarize.py
hades/topic_analysis/__init__.py
hades/topic_analysis/cca.py
hades/topic_analysis/sentence_topic_analyser.py
hades/topic_analysis/stats.py
hades/topic_modeling/__init__.py
hades/topic_modeling/model.py
hades/topic_modeling/model_optimizer/__init__.py
hades/topic_modeling/model_optimizer/model_optimizer.py
hades/topic_modeling/model_optimizer/utils.py
hades/topic_modeling/topic_probs.py
hades/topic_modeling/utils.py
hades_app/__init__.py
hades_app/config.py
hades_app/main.py
hades_app/run_app.py
hades_app/utils/__init__.py
hades_app/utils/clustering.py
hades_app/utils/plots.py
hades_app/utils/stats.py
hades_nlp-0.1.2.dist-info/entry_points.txt
hades_nlp-0.1.2.dist-info/LICENSE
hades_nlp-0.1.2.dist-info/METADATA
hades_nlp-0.1.2.dist-info/WHEEL
hades_nlp-0.1.2.dist-info/RECORD
