Metadata-Version: 2.1
Name: hades-nlp
Version: 0.1.2
Summary: Homologous Automated Document Exploration and Summarization - A powerful tool for comparing similarly structured documents
Keywords: nlp,documents,topic modeling,summarization,machine learning,natural language processing,text analysis,text mining,text summarization
Author: Artur Żółkowski
Author-email: artur.zolkowski@wp.pl
Requires-Python: >=3.9, !=2.7.*, !=3.0.*, !=3.1.*, !=3.2.*, !=3.3.*, !=3.4.*, !=3.5.*, !=3.6.*, !=3.7.*, !=3.8.*
Classifier: Programming Language :: Python :: 3
Classifier: Programming Language :: Python :: 3.9
Classifier: Programming Language :: Python :: 3.10
Classifier: Programming Language :: Python :: 3.11
Requires-Dist: PyPDF2 (>=2.6.0,<3.0.0)
Requires-Dist: altair (<5)
Requires-Dist: bert-extractive-summarizer (>=0.10.1,<0.11.0)
Requires-Dist: black (>=22.6.0,<23.0.0)
Requires-Dist: click (>=8.1.3,<9.0.0)
Requires-Dist: contextualized-topic-models (>=2.4.2,<3.0.0)
Requires-Dist: gensim (>=4.3.1,<5.0.0)
Requires-Dist: llvmlite (>=0.40.1,<0.41.0)
Requires-Dist: matplotlib (>3.5.2)
Requires-Dist: numpy (>=1.23.1,<2.0.0)
Requires-Dist: openai (>=0.23.0,<0.24.0)
Requires-Dist: pandas (>=1.4.3,<2.0.0)
Requires-Dist: plotly (>=5.9.0,<6.0.0)
Requires-Dist: pyLDAvis (>=3.3.1,<4.0.0)
Requires-Dist: pycountry (>=22.3.5,<23.0.0)
Requires-Dist: scipy (>=1.8.1,<2.0.0)
Requires-Dist: seaborn (>=0.12.2)
Requires-Dist: setuptools (>58.1.0)
Requires-Dist: spacy (>=3.3.1,<4.0.0)
Requires-Dist: st-annotated-text (>=3.0.0,<4.0.0)
Requires-Dist: statsmodels (>=0.13.2,<0.14.0)
Requires-Dist: streamlit (==1.16.0)
Requires-Dist: swifter (>=1.2.0,<2.0.0)
Requires-Dist: umap-learn (>=0.5.3,<0.6.0)
